chemged/__init__.py
chemged/chem_utils.py
chemged/chemged.py
chemged/cost.py
chemged/plotting.py
chemged/py.typed
chemged-0.1.1.dist-info/AUTHORS.md
chemged-0.1.1.dist-info/LICENSE.txt
chemged-0.1.1.dist-info/METADATA
chemged-0.1.1.dist-info/WHEEL
chemged-0.1.1.dist-info/RECORD
