Metadata-Version: 2.3
Name: chemged
Version: 0.1.1
Summary: Package calculating the approximate graph edit distance between chemicals
License: MIT
Author: James Wellnitz
Author-email: wellnitz.james@gmail.com
Maintainer: James Wellnitz
Maintainer-email: wellnitz.james@gmail.com
Requires-Python: >=3.11,<4.0
Classifier: License :: OSI Approved :: MIT License
Classifier: Natural Language :: English
Classifier: Operating System :: OS Independent
Classifier: Programming Language :: Python :: 3
Classifier: Programming Language :: Python :: 3.11
Classifier: Programming Language :: Python :: 3.12
Classifier: Programming Language :: Python :: 3.13
Requires-Dist: networkx (>=3.5,<4.0)
Requires-Dist: numpy (>=2.0.0,<3.0.0)
Requires-Dist: rdkit (>=2024.9.5,<2025.0.0)
Requires-Dist: scipy (>=1.15.3,<2.0.0)
Requires-Dist: tqdm (>=4.66.4,<5.0.0)
Project-URL: Repository, https://github.com/molecularmodelinglab/ChemGED
